radar_range_equation/MODULE_STRUCTURE.md
radar_range_equation/__init__.py
radar_range_equation/analysis.py
radar_range_equation/constants.py
radar_range_equation/converters.py
radar_range_equation/equations.py
radar_range_equation/main.py
radar_range_equation/plot.py
radar_range_equation/solvable.py
radar_range_equation/solvers.py
radar_range_equation/variables.py
radar_range_equation-2025.12.12.dev1.dist-info/METADATA
radar_range_equation-2025.12.12.dev1.dist-info/WHEEL
radar_range_equation-2025.12.12.dev1.dist-info/licenses/LICENSE
radar_range_equation-2025.12.12.dev1.dist-info/RECORD
