Metadata-Version: 2.4
Name: Radar_Range_Equation
Version: 2025.12.12.dev1
Summary: A Radar Range Equation Package
Project-URL: Homepage, https://github.com/gleatd01/Radar_Range_Equation/
Project-URL: Issues, https://github.com/gleatd01/Radar_Range_Equation/issues
Author-email: Taylor <taylor@buzzedtop.com>
License-Expression: MIT
License-File: LICENSE
Classifier: Operating System :: OS Independent
Classifier: Programming Language :: Python :: 3
Requires-Python: >=3.9
Requires-Dist: matplotlib
Requires-Dist: numpy
Requires-Dist: pint
Requires-Dist: scipy
Requires-Dist: sympy
